{
    "data": [
        {
            "_id": "5facad4d6491fd00176dd719",
            "teamData": [
                4,
                5,
                6
            ],
            "_createdOn": "2020-11-12T03:34:37.186Z"
        },
        {
            "_id": "5facad316491fd00176dd718",
            "teamData": [
                4,
                5,
                6
            ],
            "_createdOn": "2020-11-12T03:34:09.212Z"
        },
        {
            "_id": "5facacd46491fd00176dd70c",
            "teamData": [
                4,
                5,
                6
            ],
            "_createdOn": "2020-11-12T03:32:36.201Z"
        },
        {
            "_id": "5facac466491fd00176dd70b",
            "teamData": [
                4,
                5,
                6
            ],
            "_createdOn": "2020-11-12T03:30:14.706Z"
        },
        {
            "_id": "5facac3e6491fd00176dd709",
            "teamData": [
                4,
                5,
                6
            ],
            "_createdOn": "2020-11-12T03:30:06.566Z"
        },
        {
            "_id": "5facabef6491fd00176dd705",
            "teamData": [
                4,
                5,
                6
            ],
            "_createdOn": "2020-11-12T03:28:47.408Z"
        },
        {
            "_id": "5faca05e6491fd00176dd650",
            "teamData": [
                4,
                5,
                6
            ],
            "_createdOn": "2020-11-12T02:39:26.935Z"
        },
        {
            "_id": "5faca04f6491fd00176dd64f",
            "teamData": [
                4,
                5,
                6
            ],
            "_createdOn": "2020-11-12T02:39:11.674Z"
        },
        {
            "_id": "5faca04c6491fd00176dd64e",
            "teamData": [
                4,
                5,
                6
            ],
            "_createdOn": "2020-11-12T02:39:08.301Z"
        },
        {
            "_id": "5fac9fdd6491fd00176dd642",
            "teamData": [
                4,
                5,
                6
            ],
            "_createdOn": "2020-11-12T02:37:17.787Z"
        },
        {
            "_id": "5fac9f956491fd00176dd637",
            "teamData": [
                4,
                5,
                6
            ],
            "_createdOn": "2020-11-12T02:36:05.850Z"
        },
        {
            "_id": "5fac9f426491fd00176dd636",
            "teamData": [
                4,
                5,
                6
            ],
            "_createdOn": "2020-11-12T02:34:42.041Z"
        },
        {
            "_id": "5fac9f216491fd00176dd62b",
            "teamData": [
                4,
                5,
                6
            ],
            "_createdOn": "2020-11-12T02:34:09.349Z"
        },
        {
            "_id": "5fac9f126491fd00176dd629",
            "teamData": [
                4,
                5,
                6
            ],
            "_createdOn": "2020-11-12T02:33:54.911Z"
        },
        {
            "_id": "5fac9f076491fd00176dd628",
            "teamData": [
                4,
                5,
                6
            ],
            "_createdOn": "2020-11-12T02:33:43.270Z"
        },
        {
            "_id": "5fac9ef56491fd00176dd627",
            "teamData": [
                4,
                5,
                6
            ],
            "_createdOn": "2020-11-12T02:33:25.957Z"
        },
        {
            "_id": "5fac9ed86491fd00176dd626",
            "teamData": [
                4,
                5,
                6
            ],
            "_createdOn": "2020-11-12T02:32:56.476Z"
        },
        {
            "_id": "5fac9ec66491fd00176dd625",
            "teamData": [
                4,
                5,
                6
            ],
            "_createdOn": "2020-11-12T02:32:38.542Z"
        },
        {
            "_id": "5fac9e9d6491fd00176dd61a",
            "teamData": [
                4,
                5,
                6
            ],
            "_createdOn": "2020-11-12T02:31:57.109Z"
        },
        {
            "_id": "5fac9e7a6491fd00176dd618",
            "teamData": [
                4,
                5,
                6
            ],
            "_createdOn": "2020-11-12T02:31:22.836Z"
        }
    ],
    "status": 200,
    "statusText": "",
    "headers": {
        "content-type": "application/json; charset=utf-8"
    },
    "config": {
        "url": "https://jsonbox.io/box_27ac3dacb977a1e82148/data",
        "method": "get",
        "headers": {
            "Accept": "application/json, text/plain, */*"
        },
        "transformRequest": [
            null
        ],
        "transformResponse": [
            null
        ],
        "timeout": 0,
        "xsrfCookieName": "XSRF-TOKEN",
        "xsrfHeaderName": "X-XSRF-TOKEN",
        "maxContentLength": -1,
        "maxBodyLength": -1
    },
    "request": {}
}